cjs_fdc/__init__.py
cjs_fdc/cjs_fdc.py
cjs_fdc-0.0.2b1.dist-info/DESCRIPTION.rst
cjs_fdc-0.0.2b1.dist-info/METADATA
cjs_fdc-0.0.2b1.dist-info/RECORD
cjs_fdc-0.0.2b1.dist-info/WHEEL
cjs_fdc-0.0.2b1.dist-info/entry_points.txt
cjs_fdc-0.0.2b1.dist-info/metadata.json
cjs_fdc-0.0.2b1.dist-info/top_level.txt
