Metadata-Version: 2.0
Name: cjs-fdc
Version: 0.0.2b1
Summary: count the number of files or dirs in a given dir
Home-page: https://github.com/CCC-S/cjs_fdc
Author: CJS
Author-email: 0empcjs@gmail.com
License: UNKNOWN
Platform: UNKNOWN
Classifier: Development Status :: 4 - Beta
Classifier: Programming Language :: Python :: 3
Classifier: License :: OSI Approved :: MIT License
Classifier: Operating System :: POSIX :: Linux
Classifier: Operating System :: MacOS
Requires-Dist: Click
